programmable_counter.vhd
library ieee;
use ieee.std_logic_1164.all;
use ieee.numeric_std.all;

entity programmable_counter is
    generic (
        N : integer := 8  -- Width of the counter
    );
    port (
        clk     : in  std_logic;          -- Clock input
        rst_n   : in  std_logic;          -- Asynchronous reset input
        enable  : in  std_logic;          -- Enable input
        load    : in  std_logic;          -- Load input
        load_value : in  std_logic_vector(N-1 downto 0); -- Value to load into the counter
        limit_value : in  std_logic_vector(N-1 downto 0); -- Limit value for the counter
        count   : out std_logic_vector(N-1 downto 0);  -- Counter output
        limit_pulse : out std_logic          -- Limit pulse output
    );
end entity programmable_counter;

architecture rtl of programmable_counter is
    signal counter_reg : std_logic_vector(N-1 downto 0) := (others => '0');
    signal limit_reached : std_logic := '0';
    begin
        count <= counter_reg;
        limit_pulse <= limit_reached;
        process(clk, rst_n)
        begin
            if rst_n = '0' then
                counter_reg <= (others => '0');
                limit_reached <= '0';
            elsif rising_edge(clk) then 
                limit_reached <= '0';

                if load = '1' then
                    counter_reg <= load_value;

                elsif enable ='1' then
                    if (counter_reg = limit_value) then
                        counter_reg <= (others => '0');
                        limit_reached <='1';
                    else
                        counter_reg <= std_logic_vector(unsigned (counter_reg)+1);
                        limit_reached <= '0';

    end if;
    end if;
    end if;
    end process;
end architecture rtl;

tb_counter_vhdl.vhd
library ieee;
use ieee.std_logic_1164.all;
use ieee.numeric_std.all;
use std.env.all;

entity tb_programmable_counter is

end entity;

architecture simulation of tb_programmable_counter is
    constant N          : positive :=8;
    constant CLK_PERIOD : TIME := 10 ns;

    signal clk          : STD_LOGIC := '0';
    signal rst_n        : STD_LOGIC := '1';
    signal enable : STD_LOGIC := '0';
    signal load : STD_LOGIC := '0';
    signal load_value : STD_LOGIC_VECTOR(N-1 downto 0) := (others => '0') ;
    signal limit_value : STD_LOGIC_VECTOR(N-1 downto 0) := (others => '0');
    signal count : STD_LOGIC_VECTOR(N-1 downto 0) ;
    signal limit_pulse : STD_LOGIC ;
begin
    uut : entity work.programmable_counter
    generic map (
        N => N
    )
    port map (
            clk         => clk,
            rst_n       => rst_n,
            enable      => enable,
            load        => load,
            load_value  => load_value,
            limit_value => limit_value,
            count       => count,
            limit_pulse => limit_pulse
    );
    clock_process : process
    begin
        while TRUE loop
            clk <= '0';
            wait for CLK_PERIOD/2;

            clk <= '1';
            wait for CLK_PERIOD/2;
        end loop;

    end process;

    stimulus_process : process 
    begin
        rst_n <='1';
        wait for 1 ns;
        rst_n <='0';
        wait for 1 ns;
        limit_value <= STD_LOGIC_VECTOR(to_unsigned(4,N));
        load_value <= STD_LOGIC_VECTOR(to_unsigned(2,N));
        --asenkron reset test

        assert count = STD_LOGIC_VECTOR(to_unsigned(0,N))
            report "Reset Error:"
            severity FAILURE;
        
        assert limit_pulse='0'
            report "Limit_pulse is not zero"
            severity FAILURE;
        
        wait until falling_edge(clk);
        rst_n <= '1';

        load <= '1';

        wait until rising_edge(clk);
        wait for 1 ns;

        assert count = STD_LOGIC_VECTOR(to_unsigned(2,N)) 
            report "load error: expected count is 2"
            severity FAILURE;
        
        load <='0';
        enable <='1';

        wait until rising_edge(clk);
        wait for 1 ns;

        assert count = STD_LOGIC_VECTOR(to_unsigned(3,N))
            report "enable error: expected count is 3"
            severity FAILURE;

        wait until rising_edge(clk);
        wait for 1 ns;

        assert count = STD_LOGIC_VECTOR(to_unsigned(4,N))
            report "enable error: expected count is 4"
            severity FAILURE;
        
        wait until rising_edge(clk);
        wait for 1 ns;
        
            assert count = STD_LOGIC_VECTOR(to_unsigned(0,N))
            report "enable error: expected count is 0"
            severity FAILURE;
        
        assert limit_pulse = '1'
            report "LIMIT ERROR: expected limit_pulse = 1"
            severity failure;

        -- Pulse sonraki clock'ta temizlenmeli
        wait until rising_edge(clk);
        wait for 1 ns;

        assert count = std_logic_vector(to_unsigned(1, N))
            report "COUNT ERROR: expected count = 1"
            severity failure;

        assert limit_pulse = '0'
            report "PULSE ERROR: limit_pulse lasted longer than one cycle"
            severity failure;

        -- Enable kapatıldığında değer korunmalı
        enable <= '0';

        wait until rising_edge(clk);
        wait for 1 ns;

        assert count = std_logic_vector(to_unsigned(1, N))
            report "ENABLE ERROR: count changed while enable was zero"
            severity failure;

        -- Load ve enable aynı anda 1: load öncelikli
        load_value <= std_logic_vector(to_unsigned(3, N));
        load       <= '1';
        enable     <= '1';

        wait until rising_edge(clk);
        wait for 1 ns;

        assert count = std_logic_vector(to_unsigned(3, N))
            report "PRIORITY ERROR: load did not override enable"
            severity failure;

        -- Load bırakılınca 3'ten devam etmeli
        load <= '0';

        wait until rising_edge(clk);
        wait for 1 ns;

        assert count = std_logic_vector(to_unsigned(4, N))
            report "COUNT ERROR: counter did not continue from load value"
            severity failure;

        report "ALL TESTS PASSED" severity note;

        stop;
        wait;
        
        
    end process;
    

end architecture;

counter.vcd
$date
  Mon Jul 20 03:33:34 2026
$end
$version
  GHDL v0
$end
$timescale
  1 fs
$end
$scope module standard $end
$upscope $end
$scope module textio $end
$upscope $end
$scope module std_logic_1164 $end
$upscope $end
$scope module numeric_std $end
$upscope $end
$scope module env $end
$upscope $end
$scope module tb_programmable_counter $end
$var reg 1 ! clk $end
$var reg 1 " rst_n $end
$var reg 1 # enable $end
$var reg 1 $ load $end
$var reg 8 % load_value[7:0] $end
$var reg 8 & limit_value[7:0] $end
$var reg 8 ' count[7:0] $end
$var reg 1 ( limit_pulse $end
$scope module uut $end
$var reg 1 ) clk $end
$var reg 1 * rst_n $end
$var reg 1 + enable $end
$var reg 1 , load $end
$var reg 8 - load_value[7:0] $end
$var reg 8 . limit_value[7:0] $end
$var reg 8 / count[7:0] $end
$var reg 1 0 limit_pulse $end
$var reg 8 1 counter_reg[7:0] $end
$var reg 1 2 limit_reached $end
$upscope $end
$upscope $end
$enddefinitions $end
#0
0!
1"
0#
0$
b00000000 %
b00000000 &
b00000000 '
0(
0)
1*
0+
0,
b00000000 -
b00000000 .
b00000000 /
00
b00000000 1
02
#1000000
0"
0*
#2000000
b00000010 %
b00000100 &
b00000010 -
b00000100 .
#5000000
1!
1)
#10000000
0!
1"
1$
0)
1*
1,
#15000000
1!
b00000010 '
1)
b00000010 /
b00000010 1
#16000000
1#
0$
1+
0,
#20000000
0!
0)
#25000000
1!
b00000011 '
1)
b00000011 /
b00000011 1
#30000000
0!
0)
#35000000
1!
b00000100 '
1)
b00000100 /
b00000100 1
#40000000
0!
0)
#45000000
1!
b00000000 '
1(
1)
b00000000 /
10
b00000000 1
12
#50000000
0!
0)
#55000000
1!
b00000001 '
0(
1)
b00000001 /
00
b00000001 1
02
#56000000
0#
0+
#60000000
0!
0)
#65000000
1!
1)
#66000000
1#
1$
b00000011 %
1+
1,
b00000011 -
#70000000
0!
0)
#75000000
1!
b00000011 '
1)
b00000011 /
b00000011 1
#76000000
0$
0,
#80000000
0!
0)
#85000000
1!
b00000100 '
1)
b00000100 /
b00000100 1
