cdc.sv
module cdc_handshake (
    input  logic src_clk,
    input  logic dst_clk,
    input  logic rst_n,
    input  logic src_pulse,
    
    output logic src_busy,
    output logic dst_pulse
);

logic req_toggle;

logic req_sync_ff1;
logic req_sync_ff2;
logic req_sync_d;

logic ack_toggle;
logic ack_sync_ff1;
logic ack_sync_ff2;


always_comb begin 
    src_busy = (req_toggle != ack_sync_ff2);    
end

//source req
always_ff @( posedge src_clk or negedge rst_n ) begin
    if (!rst_n) begin
        req_toggle <= 1'b0;
    end else begin
        if (src_pulse && !src_busy) begin
            req_toggle <= ~req_toggle;

        end
    end
end


always_ff @( posedge dst_clk or negedge rst_n ) begin
    if (!rst_n) begin
        req_sync_ff1 <= 1'b0;
        req_sync_ff2 <= 1'b0;
    end else begin
        req_sync_ff1 <= req_toggle;
        req_sync_ff2 <= req_sync_ff1;
    end
end

//transformation ack signal     
    
always_ff @( posedge src_clk or negedge rst_n ) begin
    if (!rst_n) begin
        ack_sync_ff1 <= 1'b0;
        ack_sync_ff2 <= 1'b0;
    end else begin
        ack_sync_ff1 <= ack_toggle;
        ack_sync_ff2 <= ack_sync_ff1;
    end
end

always_ff @( posedge dst_clk or negedge rst_n ) begin
    if (!rst_n) begin
        req_sync_d <= 1'b0;
        dst_pulse <= 1'b0;
        ack_toggle <= 1'b0;
    end else begin
        req_sync_d <= req_sync_ff2;
        dst_pulse <= req_sync_d ^ req_sync_ff2;

        if (req_sync_d ^ req_sync_ff2) begin
            ack_toggle <= req_sync_ff2;
        end
    end
end


endmodule

tb_cdc.sv
`timescale 1ns/1ps

module tb_cdc;
logic src_clk;
logic dst_clk;
logic rst_n;
logic src_pulse;
logic src_busy;
logic dst_pulse;

cdc_handshake uut(
    .src_clk(src_clk),
    .dst_clk(dst_clk),
    .rst_n(rst_n),
    .src_pulse(src_pulse),
    .src_busy(src_busy),
    .dst_pulse(dst_pulse)
    
);

initial begin
    src_clk= 1'b0;
    forever #5 src_clk = ~src_clk;
end


initial begin
    dst_clk =1'b0;
    forever #10 dst_clk = ~dst_clk;
end

initial begin
    $dumpfile("tb_cdc.vcd");
    $dumpvars(0,tb_cdc);

    rst_n = 1'b0;
    src_pulse = 1'b0;

    repeat(2) @(posedge src_clk);
    @(negedge src_clk);
    rst_n = 1'b1;
    src_pulse = 1'b1;

    @(posedge src_clk);
    @(negedge src_clk);
    
    src_pulse = 1'b0;

    repeat(2) @(posedge dst_clk);
    @(negedge dst_clk);
    @(posedge dst_clk);
    #1;

    if (dst_pulse !== 1'b0) begin
        $error("dst_pulse should be low");
    end else begin
        $display("dst_pulse correct");
    end

    $finish;
end






endmodule

tb_cdc.vcd
$date
	Wed Aug 12 17:46:26 2026
$end
$version
	Icarus Verilog
$end
$timescale
	1ps
$end
$scope module tb_cdc $end
$var wire 1 ! src_busy $end
$var wire 1 " dst_pulse $end
$var reg 1 # dst_clk $end
$var reg 1 $ rst_n $end
$var reg 1 % src_clk $end
$var reg 1 & src_pulse $end
$scope module uut $end
$var wire 1 # dst_clk $end
$var wire 1 $ rst_n $end
$var wire 1 % src_clk $end
$var wire 1 & src_pulse $end
$var reg 1 ' ack_sync_ff1 $end
$var reg 1 ( ack_sync_ff2 $end
$var reg 1 ) ack_toggle $end
$var reg 1 " dst_pulse $end
$var reg 1 * req_sync_d $end
$var reg 1 + req_sync_ff1 $end
$var reg 1 , req_sync_ff2 $end
$var reg 1 - req_toggle $end
$var reg 1 ! src_busy $end
$upscope $end
$upscope $end
$enddefinitions $end
$comment Show the parameter values. $end
$dumpall
$end
#0
$dumpvars
0-
0,
0+
0*
0)
0(
0'
0&
0%
0$
0#
0"
0!
$end
#5000
1%
#10000
0%
1#
#15000
1%
#20000
1&
1$
0%
0#
#25000
1!
1-
1%
#30000
1+
0&
0%
1#
#35000
1%
#40000
0%
0#
#45000
1%
#50000
1,
0%
1#
#55000
1%
#60000
0%
0#
#65000
1%
#70000
1)
1"
1*
0%
1#
#75000
1'
1%
#80000
0%
0#
#85000
0!
1(
1%
#90000
0"
0%
1#
