fsmverilog.v
module sequence_detector (
    input wire clk,
    input wire rst_n,
    input wire valid,
    input wire bit_in,
    output reg match
);

localparam [1:0]   IDLE=2'b00,
                   S1=2'b01,
                   S10=2'b10,
                   S101=2'b11;

reg [1:0] current_state;
reg [1:0] next_state;
reg       detect;

always @(*) begin
    next_state = current_state;
    detect = 1'b0;
    if (valid) begin
    case (current_state)
        IDLE: begin
            if (bit_in) begin
                next_state = S1;
            end else begin
                next_state = IDLE;
            end
        end 
        S1:begin
                if (bit_in) begin
                        next_state = S1;
                end else begin
                        next_state = S10;
                end
            end

        S10:begin
                if (bit_in) begin
                    next_state = S101;
                end else begin
                    next_state = IDLE;
                end
            end
        S101:begin
                if(bit_in) begin
                    detect = 1'b1;
                    next_state = S1;
                end else begin
                    next_state = S10;
                end
            end
        default: begin
            next_state = IDLE;
            detect = 1'b0;
        end

    endcase
end

end

always @(posedge clk or negedge rst_n) begin
    if (!rst_n) begin
            current_state <= IDLE;
            match <= 1'b0;
        end else begin
            current_state <= next_state;
            match <= detect;
        end
end


    
endmodule

tb_fsmverilog.v
module tb_fsmver;
reg clk;
reg rst_n;
reg valid;
reg bit_in;
reg match;


sequence_detector uut(
    .clk(clk),
    .rst_n(rst_n),
    .valid(valid),
    .bit_in(bit_in),
    .match(match)
);
task send_bit;
input input_bit;
input expected_bit;
    begin
        @(negedge clk);
        bit_in = input_bit;
        valid = 1'b1;
        @(posedge clk);
        #1;
    
        if (match != expected_bit) begin
            $error("ERROR: bit=%b, match=%b, expected:%b",
            input_bit,match,expected_bit);
        end

    end
endtask

initial begin
    clk =0;
    forever #5 clk = ~clk;
end

initial begin
    $dumpfile("tb_fsmv.vcd");
    $dumpvars(0,tb_fsmver);

    rst_n = 1'b0;
    valid = 1'b0;
    bit_in = 1'b0;
    repeat(2) @(posedge clk);
        @(negedge clk);

        rst_n = 1'b1;

        send_bit(1'b1, 1'b0);
        send_bit(1'b0, 1'b0);
        send_bit(1'b1, 1'b0);
        send_bit(1'b1, 1'b1);

        send_bit(1'b0, 1'b0);
        send_bit(1'b1, 1'b0);
        send_bit(1'b1, 1'b1);
        @(negedge clk);
        valid = 1'b0;
        bit_in =1'b0;

        $display("TEST COMPLETED");
        $finish;
end

endmodule

tb_fsmv.vcd
$date
	Tue Jul 21 04:08:10 2026
$end
$version
	Icarus Verilog
$end
$timescale
	1s
$end
$scope module tb_fsmver $end
$var wire 1 ! match $end
$var reg 1 " bit_in $end
$var reg 1 # clk $end
$var reg 1 $ rst_n $end
$var reg 1 % valid $end
$scope module uut $end
$var wire 1 " bit_in $end
$var wire 1 # clk $end
$var wire 1 $ rst_n $end
$var wire 1 % valid $end
$var parameter 2 & IDLE $end
$var parameter 2 ' S1 $end
$var parameter 2 ( S10 $end
$var parameter 2 ) S101 $end
$var reg 2 * current_state [1:0] $end
$var reg 1 + detect $end
$var reg 1 ! match $end
$var reg 2 , next_state [1:0] $end
$upscope $end
$scope task send_bit $end
$var reg 1 - expected_bit $end
$var reg 1 . input_bit $end
$upscope $end
$upscope $end
$enddefinitions $end
$comment Show the parameter values. $end
$dumpall
b11 )
b10 (
b1 '
b0 &
$end
#0
$dumpvars
x.
x-
b0 ,
0+
b0 *
0%
0$
0#
0"
0!
$end
#5
1#
#10
0#
#15
1#
#20
0-
1.
1$
0#
#25
1#
#30
b1 ,
1%
1"
0#
#35
b1 *
1#
#36
0.
#40
b10 ,
0"
0#
#45
b0 ,
b10 *
1#
#46
1.
#50
b11 ,
1"
0#
#55
b1 ,
1+
b11 *
1#
#56
1-
#60
0#
#65
0+
1!
b1 *
1#
#66
0-
0.
#70
b10 ,
0"
0#
#75
b0 ,
0!
b10 *
1#
#76
1.
#80
b11 ,
1"
0#
#85
b1 ,
1+
b11 *
1#
#86
1-
#90
0#
#95
0+
1!
b1 *
1#
#100
0"
0%
0#
