FSMvhdl.vhd
library ieee;
use ieee.std_logic_1164.all;


entity sequence_detector_1011 is
    port (
        clk   : in std_logic;
        rst_n : in std_logic;
        valid : in std_logic;
        bit_in  : in  std_logic;
        match   : out std_logic
    
    );
end entity sequence_detector_1011;

architecture rtl of sequence_detector_1011 is
    type state_t is(
        IDLE,
        S1,
        S10,
        S101
    );

    signal current_state : state_t;
    signal next_state    : state_t;
    signal detected_comb : STD_LOGIC;
    signal matched_reg   : STD_LOGIC;

begin

    match <= matched_reg;

    --Next state combinational logic

    combinational_process : process (current_state, valid, bit_in)
    begin
        next_state <= current_state;
        detected_comb <= '0';
        
        if valid ='1' then
            case current_state is
                when IDLE =>
                    
                    if bit_in='1' then
                        next_state <= S1;
                        
                    else
                         next_state <= IDLE;
                    end if;

                when S1 =>
                    if bit_in='1' then
                        next_state <= S1;
                    else
                        next_state <= S10;
                    end if;
                
                when S10 =>
                    if bit_in='1' then
                        next_state <=S101;
                    else
                        next_state <= IDLE;
                    end if;
                
                when S101 =>
                    if bit_in='1' then
                        detected_comb <= '1';
                        next_state <=S1;
                    else
                        next_state <= S10;    
                    end if;

                when others =>
                    next_state <= IDLE;
                    detected_comb <= '0';
                    null;
            end case;
            
        end if ;
        
    end process;

    sequential_process : process (clk,rst_n)
    begin
        if rst_n='0' then
            current_state <= IDLE;
            matched_reg <= '0';
        elsif rising_edge(clk) then
            current_state <= next_state;
            matched_reg <=detected_comb;

        end if;
    end process;
end architecture rtl;

tb_fsmvhdl.vhd
library ieee;
use ieee.std_logic_1164.all;
use std.env.all;

entity tb_fsmvhdl is
    
end entity;

architecture simulation of tb_fsmvhdl is
    constant CLK_PERIOD : time := 10 ns;
    signal clk : STD_LOGIC := '0';
    signal rst_n : STD_LOGIC := '1';
    signal valid : STD_LOGIC := '0';
    signal bit_in : STD_LOGIC := '0';
    signal match : STD_LOGIC;
begin
    uut : entity work.sequence_detector_1011
        port map (
            clk => clk,
            rst_n => rst_n,
            valid => valid,
            bit_in => bit_in,
            match => match

        );
    clock_process : process
    begin
        while TRUE  loop
            clk <= '0';
            wait for CLK_PERIOD/2;
            clk <= '1';
            wait for CLK_PERIOD/2;
        end loop;
    end process;
    


    stimulus_process : process
    
        procedure send_bit (
            constant input_bit : in std_logic;
            constant expected_match : in std_logic
        ) is
        begin
            wait until falling_edge(clk);

            bit_in <= input_bit;
            valid <='1';

            wait until rising_edge(clk);
            wait for 1 ns;

            assert match=expected_match
                report
                    "ERROR: bit_in=" &
                    std_logic'image(input_bit) &
                    ", match=" &
                    std_logic'image(match) &
                    ", expected=" &
                    std_logic'image(expected_match)
                severity error;

        end procedure;


    begin

        rst_n  <='0';
        valid  <='0';
        bit_in <='0';

        wait until rising_edge(clk);
        wait until rising_edge(clk);

        wait until rising_edge(clk);
        rst_n <= '1';

        --1011011
        send_bit('1','0');
        send_bit('0','0');
        send_bit('1','0');
        send_bit('1','1');

        send_bit('0','0');
        send_bit('1','0');
        send_bit('1','1');
        
        wait until falling_edge(clk);

        valid <='0';
        bit_in <= '0';
        
        report "ALL TEST COMPLETED";
        finish;
        
        
    end process;
end architecture;

tb_fsmvhdl.vcd
$date
  Wed Jul 22 03:21:51 2026
$end
$version
  GHDL v0
$end
$timescale
  1 fs
$end
$scope module standard $end
$upscope $end
$scope module textio $end
$upscope $end
$scope module std_logic_1164 $end
$upscope $end
$scope module env $end
$upscope $end
$scope module tb_fsmvhdl $end
$var reg 1 ! clk $end
$var reg 1 " rst_n $end
$var reg 1 # valid $end
$var reg 1 $ bit_in $end
$var reg 1 % match $end
$scope module uut $end
$var reg 1 & clk $end
$var reg 1 ' rst_n $end
$var reg 1 ( valid $end
$var reg 1 ) bit_in $end
$var reg 1 * match $end
$comment current_state is not handled $end
$comment next_state is not handled $end
$var reg 1 + detected_comb $end
$var reg 1 , matched_reg $end
$upscope $end
$upscope $end
$enddefinitions $end
#0
0!
0"
0#
0$
0%
0&
0'
0(
0)
0*
0+
0,
#5000000
1!
1&
#10000000
0!
0&
#15000000
1!
1&
#20000000
0!
0&
#25000000
1!
1"
1&
1'
#30000000
0!
1#
1$
0&
1(
1)
#35000000
1!
1&
#40000000
0!
0$
0&
0)
#45000000
1!
1&
#50000000
0!
1$
0&
1)
#55000000
1!
1&
1+
#60000000
0!
0&
#65000000
1!
1%
1&
1*
0+
1,
#70000000
0!
0$
0&
0)
#75000000
1!
0%
1&
0*
0,
#80000000
0!
1$
0&
1)
#85000000
1!
1&
1+
#90000000
0!
0&
#95000000
1!
1%
1&
1*
0+
1,
