valid_handshake.sv
module valid_handshake (
    input logic clk,
    input logic rst_n,
    input logic in_valid,
    input logic [7:0] in_data,
    input logic out_ready,

    output logic in_ready,
    output logic out_valid,
    output logic [7:0] out_data

);
logic [7:0] data_reg;
logic full_reg;
logic push;
logic pop;


always_comb begin
    out_data = data_reg;
    out_valid = full_reg;
    in_ready = !full_reg || out_ready;
end
assign push = in_valid && in_ready;
assign pop = out_valid && out_ready;

always_ff @(posedge clk or negedge rst_n ) begin
    if (!rst_n) begin
        data_reg <= 8'b00000000;
        full_reg <= 1'b0;
    end else if (push == 1'b1 && pop == 1'b0) begin
        data_reg <= in_data;
        full_reg <= 1'b1;
    end else if (push == 1'b0 && pop == 1'b1) begin
        full_reg <= 1'b0;
    end else if (push == 1'b1 && pop == 1'b1) begin
        data_reg <= in_data;
        full_reg <= 1'b1;
    end
        
end
    
endmodule

tb_handshake.sv
`timescale 1ns/1ps

module tb_handshake;
    logic clk;
    logic rst_n;
    logic in_valid;
    logic [7:0] in_data;
    logic out_ready;

    logic in_ready;
    logic out_valid;
    logic [7:0] out_data;

    valid_handshake uut(
        .clk(clk),
        .rst_n(rst_n),
        .in_valid(in_valid),
        .in_data(in_data),
        .out_ready(out_ready),
        .in_ready(in_ready),
        .out_valid(out_valid),
        .out_data(out_data)

    );
    //TASKS


    //CLK
    initial begin
        clk=0;
        forever #5 clk=~clk;
    end

    //INITIAL PHASE
    initial begin
        $dumpfile("tb_handshake.vcd");
        $dumpvars(0, tb_handshake);
        
        rst_n = 1'b0;
        in_valid = 1'b0;
        in_data = 8'b00000000;
        out_ready = 1'b0;
        repeat(2) @(posedge clk);
        rst_n = 1'b1;
        @(negedge clk);
        if(out_valid !== 1'b0) begin
            $error("Error: out_valid should be 0 after reset");
        end
        if(in_ready !== 1'b1) begin
            $error("Error: in_ready should be 1 after reset");
        end


        @(negedge clk);
        in_valid =1;
        in_data= 8'd25;

        @(posedge clk);
        @(negedge clk);
        in_valid = 1'b0;

        if(out_valid !== 1'b1) begin
            $error("Error: out_valid should be 1 after push");
        end

        if(out_data !== 8'd25) begin
            $error("Error: out_data should be 25 after push");
        end

         if (in_ready !== 1'b0)
            $error("Error: in_ready should be 0 while buffer is full and out_ready is 0");

        @(negedge clk);
        out_ready = 1'b1;

        @(posedge clk);
        @(negedge clk);
        out_ready = 1'b0;

        if (out_valid !==1'b0) begin
            $error("Error: out_valid should be 0 after pop");
        end

        if (in_ready !== 1'b1) begin
            $error("Error: in_ready should be 1 after pop");
        end
        
        @(negedge clk);
        
        in_valid = 1'b1;
        in_data = 8'd50;
        
        $finish;

    end
endmodule

tb_handshake.vcd
$date
	Thu Jul 30 00:18:52 2026
$end
$version
	Icarus Verilog
$end
$timescale
	1ps
$end
$scope module tb_handshake $end
$var wire 1 ! out_valid $end
$var wire 8 " out_data [7:0] $end
$var wire 1 # in_ready $end
$var reg 1 $ clk $end
$var reg 8 % in_data [7:0] $end
$var reg 1 & in_valid $end
$var reg 1 ' out_ready $end
$var reg 1 ( rst_n $end
$scope module uut $end
$var wire 1 $ clk $end
$var wire 8 ) in_data [7:0] $end
$var wire 1 & in_valid $end
$var wire 1 ' out_ready $end
$var wire 1 * pop $end
$var wire 1 + push $end
$var wire 1 ( rst_n $end
$var reg 8 , data_reg [7:0] $end
$var reg 1 - full_reg $end
$var reg 1 # in_ready $end
$var reg 8 . out_data [7:0] $end
$var reg 1 ! out_valid $end
$upscope $end
$upscope $end
$enddefinitions $end
$comment Show the parameter values. $end
$dumpall
$end
#0
$dumpvars
b0 .
0-
b0 ,
0+
0*
b0 )
0(
0'
0&
b0 %
0$
1#
b0 "
0!
$end
#5000
1$
#10000
0$
#15000
1(
1$
#20000
0$
#25000
1$
#30000
1+
b11001 %
b11001 )
1&
0$
#35000
0+
0#
1!
b11001 "
b11001 .
1-
b11001 ,
1$
#40000
0&
0$
#45000
1$
#50000
1*
1#
1'
0$
#55000
0*
0!
0-
1$
#60000
0'
0$
