pulse_sync.sv
module pulse_sync (
    input logic src_clk,
    input logic dst_clk,
    input logic rst_n,
    input logic pulse_in,

    output logic pulse_out
);

logic src_toggle;
logic sync_ff1, sync_ff2, sync_ff2_d;


//source domain
always_ff @( posedge src_clk or negedge rst_n ) begin
    if (!rst_n) begin
        src_toggle <= 1'b0;
    end else if (pulse_in) begin
        src_toggle <= ~src_toggle;
    end
end
//sync domain
always_ff @( posedge dst_clk or negedge rst_n ) begin
    if (!rst_n) begin
        sync_ff1 <= 1'b0;
        sync_ff2 <= 1'b0;
        sync_ff2_d <= 1'b0;
    end else begin
        sync_ff1 <= src_toggle;
        sync_ff2 <= sync_ff1;
        sync_ff2_d <= sync_ff2;
    end
end

assign pulse_out = sync_ff2 ^ sync_ff2_d;



endmodule

tb_pulse_sync.sv
`timescale 1ns/1ps

module tb_pulse;

    logic src_clk;
    logic dst_clk;
    logic rst_n;
    logic pulse_in;
    logic pulse_out;

    integer pulse_count;

    pulse_sync uut (
        .src_clk   (src_clk),
        .dst_clk   (dst_clk),
        .rst_n     (rst_n),
        .pulse_in  (pulse_in),
        .pulse_out (pulse_out)
    );

    // src_clk period: 10 ns
    initial begin
        src_clk = 1'b0;
        forever #5 src_clk = ~src_clk;
    end

    // dst_clk period: 50 ns
    initial begin
        dst_clk = 1'b0;
        forever #25 dst_clk = ~dst_clk;
    end

    always @(posedge dst_clk or negedge rst_n) begin
        if (!rst_n)
            pulse_count <= 0;
        else if (pulse_out)
            pulse_count <= pulse_count + 1;
    end

    initial begin
        $dumpfile("tb_pulse.vcd");
        $dumpvars(0, tb_pulse);

        rst_n    = 1'b0;
        pulse_in = 1'b0;

        repeat (2) @(posedge src_clk);
        @(negedge src_clk);
        rst_n = 1'b1;

        /*
         * Bir dst_clk posedge'inden hemen sonra başlıyoruz.
         * Böylece iki toggle değişimi bir sonraki dst_clk
         * posedge'inden önce gerçekleşecek.
         */
        @(posedge dst_clk);

        // Birinci pulse
        @(negedge src_clk);
        pulse_in = 1'b1;

        @(negedge src_clk);
        pulse_in = 1'b0;

        // İkinci pulse: hedefi beklemeden gönderiliyor
        @(negedge src_clk);
        pulse_in = 1'b1;

        @(negedge src_clk);
        pulse_in = 1'b0;

        repeat (5) @(posedge dst_clk);
        @(negedge dst_clk);

        $display(
            "Sent 2 fast pulses, received %0d pulses",
            pulse_count
        );

        if (pulse_count < 2)
            $display(
                "Expected result: destination missed pulse(s)"
            );
        else
            $display(
                "Both pulses were captured in this simulation"
            );

        $finish;
    end

endmodule

tb_pulse.vcd
$date
	Wed Aug 12 02:02:07 2026
$end
$version
	Icarus Verilog
$end
$timescale
	1ps
$end
$scope module tb_pulse $end
$var wire 1 ! pulse_out $end
$var reg 1 " dst_clk $end
$var reg 1 # pulse_in $end
$var reg 1 $ rst_n $end
$var reg 1 % src_clk $end
$var integer 32 & pulse_count [31:0] $end
$scope module uut $end
$var wire 1 " dst_clk $end
$var wire 1 # pulse_in $end
$var wire 1 ! pulse_out $end
$var wire 1 $ rst_n $end
$var wire 1 % src_clk $end
$var reg 1 ' src_toggle $end
$var reg 1 ( sync_ff1 $end
$var reg 1 ) sync_ff2 $end
$var reg 1 * sync_ff2_d $end
$upscope $end
$upscope $end
$enddefinitions $end
$comment Show the parameter values. $end
$dumpall
$end
#0
$dumpvars
0*
0)
0(
0'
b0 &
0%
0$
0#
0"
0!
$end
#5000
1%
#10000
0%
#15000
1%
#20000
1$
0%
#25000
1%
1"
#30000
1#
0%
#35000
1'
1%
#40000
0#
0%
#45000
1%
#50000
1#
0%
0"
#55000
0'
1%
#60000
0#
0%
