sync_fifo.sv
module sync_fifo #(
    parameter int unsigned WIDTH = 8,
    parameter int unsigned DEPTH = 8
) (
    input logic              clk,
    input logic              rst_n,
    input logic              wr_en,
    input logic              rd_en,
    input logic [WIDTH-1:0]  data_in,

    output logic [WIDTH-1:0] data_out,
    output logic             full,
    output logic             empty
);
    localparam int PTR_WIDTH   = $clog2(DEPTH);
    localparam int COUNT_WIDTH = $clog2(DEPTH + 1);
    logic [WIDTH-1:0] memory [0:DEPTH-1];
    logic [PTR_WIDTH-1:0] write_ptr;
    logic [PTR_WIDTH-1:0] read_ptr;
    logic [COUNT_WIDTH-1:0] count;


    assign full = (count==DEPTH);
    assign empty = (count==0);

    always_ff @(posedge clk or negedge rst_n ) begin

        if (!rst_n) begin
           write_ptr <='0;
           read_ptr  <='0;
           count     <='0;
           data_out  <= '0; 
        end else begin
            if (wr_en && !full) begin
                memory[write_ptr] <= data_in;
                write_ptr <= write_ptr + 1'b1;
            end
            if (rd_en && !empty) begin
                data_out <= memory[read_ptr];
                read_ptr <= read_ptr + 1'b1;
            end
            case ({wr_en && !full, rd_en && !empty})
                2'b10: count <= count + 1'b1;
                2'b01: count <= count - 1'b1;
                2'b11: count <= count;
                2'b00: count <= count;
            endcase
            
        end


    end
endmodule

tb_fifo.sv
`timescale 1ns/1ps

module tb_sync_fifo;

    localparam int WIDTH = 8;
    localparam int DEPTH = 8;

    logic clk;
    logic rst_n;
    logic wr_en;
    logic rd_en;
    logic [WIDTH-1:0] data_in;

    logic [WIDTH-1:0] data_out;
    logic full;
    logic empty;

    logic [WIDTH-1:0] received_data;
    logic [WIDTH-1:0] previous_data;

    sync_fifo #(
        .WIDTH(WIDTH),
        .DEPTH(DEPTH)
    ) dut (
        .clk     (clk),
        .rst_n   (rst_n),
        .wr_en   (wr_en),
        .rd_en   (rd_en),
        .data_in (data_in),
        .data_out(data_out),
        .full    (full),
        .empty   (empty)
    );

    // Clock üretimi
    initial begin
        clk = 1'b0;
        forever #5 clk = ~clk;
    end

    // FIFO'yu resetleme
    task automatic reset_fifo;
        begin
            @(negedge clk);

            rst_n   = 1'b0;
            wr_en   = 1'b0;
            rd_en   = 1'b0;
            data_in = '0;

            repeat (2) @(posedge clk);

            @(negedge clk);
            rst_n = 1'b1;

            @(negedge clk);
        end
    endtask

    // FIFO'ya bir veri yazma
    task automatic write_fifo(
        input logic [WIDTH-1:0] write_data
    );
        begin
            if (full) begin
                $error("FIFO doluyken normal write_fifo task'i cagirildi");
            end else begin
                @(negedge clk);
                data_in = write_data;
                wr_en   = 1'b1;

                // DUT bu posedge'de veriyi yazar
                @(posedge clk);
                @(negedge clk);

                wr_en = 1'b0;
            end
        end
    endtask

    // FIFO'dan bir veri okuma
    task automatic read_fifo(
        output logic [WIDTH-1:0] read_data
    );
        begin
            if (empty) begin
                $error("FIFO bosken normal read_fifo task'i cagirildi");
                read_data = 'x;
            end else begin
                @(negedge clk);
                rd_en = 1'b1;

                // DUT bu posedge'de data_out'u günceller
                @(posedge clk);
                @(negedge clk);

                read_data = data_out;
                rd_en     = 1'b0;
            end
        end
    endtask

    // Okunan veriyi beklenen veriyle karşılaştırma
    task automatic check_data(
        input logic [WIDTH-1:0] expected_data,
        input logic [WIDTH-1:0] actual_data
    );
        begin
            if (actual_data !== expected_data) begin
                $error(
                    "Data mismatch! Expected=%h, Actual=%h",
                    expected_data,
                    actual_data
                );
            end else begin
                $display(
                    "Data correct: Expected=%h, Actual=%h",
                    expected_data,
                    actual_data
                );
            end
        end
    endtask

    // Aynı clock'ta okuma ve yazma
    task automatic simultaneous_read_write(
        input  logic [WIDTH-1:0] write_data,
        output logic [WIDTH-1:0] read_data
    );
        begin
            if (empty || full) begin
                $error(
                    "Simultaneous test icin FIFO ne bos ne de dolu olmali"
                );
            end else begin
                @(negedge clk);

                data_in = write_data;
                wr_en   = 1'b1;
                rd_en   = 1'b1;

                @(posedge clk);
                @(negedge clk);

                read_data = data_out;

                wr_en = 1'b0;
                rd_en = 1'b0;
            end
        end
    endtask

    initial begin
        rst_n   = 1'b1;
        wr_en   = 1'b0;
        rd_en   = 1'b0;
        data_in = '0;

        // -------------------------------------------------
        // TEST 1: Reset sonrasında empty=1, full=0
        // -------------------------------------------------

        $display("\nTEST 1: Reset kontrolu");

        reset_fifo();

        if (empty !== 1'b1)
            $error("Reset sonrasinda empty=1 olmadi");

        if (full !== 1'b0)
            $error("Reset sonrasinda full=0 olmadi");

        // -------------------------------------------------
        // TEST 2: Tek veri yazma ve okuma
        // -------------------------------------------------

        $display("\nTEST 2: Tek veri yazma/okuma");

        write_fifo(8'hA5);
        read_fifo(received_data);
        check_data(8'hA5, received_data);

        if (empty !== 1'b1)
            $error("Tek veri okunduktan sonra FIFO bos olmadi");

        // -------------------------------------------------
        // TEST 3: FIFO sirasi
        // -------------------------------------------------

        $display("\nTEST 3: FIFO sirasi");

        reset_fifo();

        write_fifo(8'h11);
        write_fifo(8'h22);
        write_fifo(8'h33);

        read_fifo(received_data);
        check_data(8'h11, received_data);

        read_fifo(received_data);
        check_data(8'h22, received_data);

        read_fifo(received_data);
        check_data(8'h33, received_data);

        // -------------------------------------------------
        // TEST 4: FIFO'yu tamamen doldurma
        // -------------------------------------------------

        $display("\nTEST 4: Full kontrolu");

        reset_fifo();

        for (int i = 0; i < DEPTH; i++) begin
            write_fifo(i);
        end

        if (full !== 1'b1)
            $error("DEPTH kadar veri yazilmasina ragmen full=1 olmadi");
        else
            $display("Full testi basarili");

        // -------------------------------------------------
        // TEST 5: Doluyken fazladan yazma
        // -------------------------------------------------

        $display("\nTEST 5: Doluyken yazma engelleme");

        // write_fifo task'ını kullanmıyoruz çünkü full iken
        // yazmayı özellikle denemek istiyoruz.
        @(negedge clk);
        data_in = 8'hEE;
        wr_en   = 1'b1;

        @(posedge clk);
        @(negedge clk);

        wr_en = 1'b0;

        if (full !== 1'b1)
            $error("Gecersiz yazmadan sonra full bozuldu");

        // FIFO'yu boşalt. EE hiçbir zaman çıkmamalı.
        for (int i = 0; i < DEPTH; i++) begin
            read_fifo(received_data);
            check_data(i, received_data);
        end

        // -------------------------------------------------
        // TEST 6: Tamamen boşaltma
        // -------------------------------------------------

        $display("\nTEST 6: Empty kontrolu");

        if (empty !== 1'b1)
            $error("Tum veriler okundugu halde empty=1 olmadi");
        else
            $display("Empty testi basarili");

        // -------------------------------------------------
        // TEST 7: Boşken fazladan okuma
        // -------------------------------------------------

        $display("\nTEST 7: Bosken okuma engelleme");

        previous_data = data_out;

        @(negedge clk);
        rd_en = 1'b1;

        @(posedge clk);
        @(negedge clk);

        rd_en = 1'b0;

        if (empty !== 1'b1)
            $error("Gecersiz okumadan sonra empty bozuldu");

        if (data_out !== previous_data)
            $error("Bosken okuma data_out degerini degistirdi");
        else
            $display("Bosken okuma basariyla engellendi");

        // -------------------------------------------------
        // TEST 8: Aynı anda okuma ve yazma
        // -------------------------------------------------

        $display("\nTEST 8: Ayni anda okuma ve yazma");

        reset_fifo();

        write_fifo(8'hA1);
        write_fifo(8'hB2);

        // A1 okunurken C3 yazılacak
        simultaneous_read_write(8'hC3, received_data);
        check_data(8'hA1, received_data);

        // FIFO'da artık B2 ve C3 olmalı
        read_fifo(received_data);
        check_data(8'hB2, received_data);

        read_fifo(received_data);
        check_data(8'hC3, received_data);

        if (empty !== 1'b1)
            $error("Simultaneous test sonrasinda FIFO bos olmadi");

        $display("\nALL FIFO TESTS PASSED");
        $finish;
    end

    initial begin
        $dumpfile("tb_sync_fifo.vcd");
        $dumpvars(0, tb_sync_fifo);
    end

endmodule

tb_sync_fifo.vcd
$date
	Sat Jul 25 04:41:07 2026
$end
$version
	Icarus Verilog
$end
$timescale
	1ps
$end
$scope module tb_sync_fifo $end
$var wire 1 ! full $end
$var wire 1 " empty $end
$var wire 8 # data_out [7:0] $end
$var parameter 32 $ DEPTH $end
$var parameter 32 % WIDTH $end
$var reg 1 & clk $end
$var reg 8 ' data_in [7:0] $end
$var reg 8 ( previous_data [7:0] $end
$var reg 1 ) rd_en $end
$var reg 8 * received_data [7:0] $end
$var reg 1 + rst_n $end
$var reg 1 , wr_en $end
$scope module dut $end
$var wire 1 & clk $end
$var wire 8 - data_in [7:0] $end
$var wire 1 ) rd_en $end
$var wire 1 + rst_n $end
$var wire 1 , wr_en $end
$var wire 1 ! full $end
$var wire 1 " empty $end
$var parameter 32 . COUNT_WIDTH $end
$var parameter 32 / DEPTH $end
$var parameter 32 0 PTR_WIDTH $end
$var parameter 32 1 WIDTH $end
$var reg 4 2 count [3:0] $end
$var reg 8 3 data_out [7:0] $end
$var reg 3 4 read_ptr [2:0] $end
$var reg 3 5 write_ptr [2:0] $end
$upscope $end
$scope begin $ivl_for_loop0 $end
$var integer 32 6 i [31:0] $end
$upscope $end
$scope begin $ivl_for_loop1 $end
$var integer 32 7 i [31:0] $end
$upscope $end
$scope task check_data $end
$upscope $end
$scope task read_fifo $end
$upscope $end
$scope task reset_fifo $end
$upscope $end
$scope task simultaneous_read_write $end
$upscope $end
$scope task write_fifo $end
$upscope $end
$upscope $end
$enddefinitions $end
$comment Show the parameter values. $end
$dumpall
b1000 1
b11 0
b1000 /
b100 .
b1000 %
b1000 $
$end
#0
$dumpvars
b0 7
b0 6
bx 5
bx 4
bx 3
bx 2
b0 -
0,
1+
bx *
0)
bx (
b0 '
0&
bx #
x"
x!
$end
#5000
1&
#10000
b0 #
b0 3
0!
1"
b0 2
b0 4
b0 5
0+
0&
#15000
1&
#20000
0&
#25000
1&
#30000
1+
0&
#35000
1&
#40000
0&
#45000
1&
#50000
1,
b10100101 '
b10100101 -
0&
#55000
0"
b1 2
b1 5
1&
#60000
0,
0&
#65000
1&
#70000
1)
0&
#75000
1"
b0 2
b1 4
b10100101 #
b10100101 3
1&
#80000
b10100101 *
0)
0&
#85000
1&
#90000
b0 #
b0 3
b0 4
b0 5
b0 '
b0 -
0+
0&
#95000
1&
#100000
0&
#105000
1&
#110000
1+
0&
#115000
1&
#120000
0&
#125000
1&
#130000
1,
b10001 '
b10001 -
0&
#135000
0"
b1 2
b1 5
1&
#140000
0,
0&
#145000
1&
#150000
1,
b100010 '
b100010 -
0&
#155000
b10 2
b10 5
1&
#160000
0,
0&
#165000
1&
#170000
1,
b110011 '
b110011 -
0&
#175000
b11 2
b11 5
1&
#180000
0,
0&
#185000
1&
#190000
1)
0&
#195000
b10 2
b1 4
b10001 #
b10001 3
1&
#200000
b10001 *
0)
0&
#205000
1&
#210000
1)
0&
#215000
b1 2
b10 4
b100010 #
b100010 3
1&
#220000
b100010 *
0)
0&
#225000
1&
#230000
1)
0&
#235000
1"
b0 2
b11 4
b110011 #
b110011 3
1&
#240000
b110011 *
0)
0&
#245000
1&
#250000
b0 #
b0 3
b0 4
b0 5
b0 '
b0 -
0+
0&
#255000
1&
#260000
0&
#265000
1&
#270000
1+
0&
#275000
1&
#280000
0&
#285000
1&
#290000
1,
0&
#295000
0"
b1 2
b1 5
1&
#300000
b1 6
0,
0&
#305000
1&
#310000
1,
b1 '
b1 -
0&
#315000
b10 2
b10 5
1&
#320000
b10 6
0,
0&
#325000
1&
#330000
1,
b10 '
b10 -
0&
#335000
b11 2
b11 5
1&
#340000
b11 6
0,
0&
#345000
1&
#350000
1,
b11 '
b11 -
0&
#355000
b100 2
b100 5
1&
#360000
b100 6
0,
0&
#365000
1&
#370000
1,
b100 '
b100 -
0&
#375000
b101 2
b101 5
1&
#380000
b101 6
0,
0&
#385000
1&
#390000
1,
b101 '
b101 -
0&
#395000
b110 2
b110 5
1&
#400000
b110 6
0,
0&
#405000
1&
#410000
1,
b110 '
b110 -
0&
#415000
b111 2
b111 5
1&
#420000
b111 6
0,
0&
#425000
1&
#430000
1,
b111 '
b111 -
0&
#435000
1!
b1000 2
b0 5
1&
#440000
b1000 6
0,
0&
#445000
1&
#450000
1,
b11101110 '
b11101110 -
0&
#455000
1&
#460000
0,
0&
#465000
1&
#470000
1)
0&
#475000
0!
b111 2
b1 4
1&
#480000
b1 7
b0 *
0)
0&
#485000
1&
#490000
1)
0&
#495000
b110 2
b10 4
b1 #
b1 3
1&
#500000
b10 7
b1 *
0)
0&
#505000
1&
#510000
1)
0&
#515000
b101 2
b11 4
b10 #
b10 3
1&
#520000
b11 7
b10 *
0)
0&
#525000
1&
#530000
1)
0&
#535000
b100 2
b100 4
b11 #
b11 3
1&
#540000
b100 7
b11 *
0)
0&
#545000
1&
#550000
1)
0&
#555000
b11 2
b101 4
b100 #
b100 3
1&
#560000
b101 7
b100 *
0)
0&
#565000
1&
#570000
1)
0&
#575000
b10 2
b110 4
b101 #
b101 3
1&
#580000
b110 7
b101 *
0)
0&
#585000
1&
#590000
1)
0&
#595000
b1 2
b111 4
b110 #
b110 3
1&
#600000
b111 7
b110 *
0)
0&
#605000
1&
#610000
1)
0&
#615000
1"
b0 2
b0 4
b111 #
b111 3
1&
#620000
b111 (
b1000 7
b111 *
0)
0&
#625000
1&
#630000
1)
0&
#635000
1&
#640000
0)
0&
#645000
1&
#650000
b0 #
b0 3
b0 '
b0 -
0+
0&
#655000
1&
#660000
0&
#665000
1&
#670000
1+
0&
#675000
1&
#680000
0&
#685000
1&
#690000
1,
b10100001 '
b10100001 -
0&
#695000
0"
b1 2
b1 5
1&
#700000
0,
0&
#705000
1&
#710000
1,
b10110010 '
b10110010 -
0&
#715000
b10 2
b10 5
1&
#720000
0,
0&
#725000
1&
#730000
1)
1,
b11000011 '
b11000011 -
0&
#735000
b1 4
b10100001 #
b10100001 3
b11 5
1&
#740000
b10100001 *
0)
0,
0&
#745000
1&
#750000
1)
0&
#755000
b1 2
b10 4
b10110010 #
b10110010 3
1&
#760000
b10110010 *
0)
0&
#765000
1&
#770000
1)
0&
#775000
1"
b0 2
b11 4
b11000011 #
b11000011 3
1&
#780000
b11000011 *
0)
0&
