2_ff.sv
module two_ff (
    input logic clk,
    input logic rst_n,
    input logic async_in,

    output logic sync_out
);
    
    logic ff1, ff2;

    always_ff @(posedge clk or negedge rst_n) begin
        if (!rst_n) begin
            ff1 <= 1'b0;
            ff2 <= 1'b0;
        end else begin
            ff1 <= async_in;
            ff2 <= ff1;
        end
    end

    assign sync_out = ff2;
endmodule

two_ff_tb.sv
module tb_two_ff;
logic clk;
logic rst_n;
logic async_in;
logic sync_out;

two_ff uut(
    .clk(clk),
    .rst_n(rst_n),
    .async_in(async_in),
    .sync_out(sync_out)
);

initial begin
    clk = 0;
    forever #5 clk = ~clk;
end

initial begin  
    $dumpfile("tb_two_ff.vcd");
    $dumpvars(0, tb_two_ff);

    rst_n = 1'b0;
    async_in = 1'b0;

    repeat(2) @(posedge clk);
    @(negedge clk);
    rst_n = 1'b1;
    
    if(sync_out !== 1'b0) begin
        $error("Error: sync_out should be 0 after reset");
    end
    // Test 1: async_in = 1
    @(negedge clk);
    async_in = 1'b1;
    @(posedge clk);
    @(negedge clk);
    if(sync_out !== 1'b0) begin
        $error("Error: sync_out should be 0 after first clock cycle");
    end
    @(posedge clk);
    @(negedge clk);
    if(sync_out !== 1'b1) begin
        $error("Error: sync_out should be 1 after second clock cycle");
    end

    async_in = 1'b0;
    repeat (2) @(posedge clk);
    @(negedge clk);
    #1;
    async_in = 1'b1;
    #3;
    async_in = 1'b0;
    repeat (2) @(posedge clk);
    @(negedge clk);

    if(sync_out !== 1'b0) begin
        $error("Error: sync_out should be 0 after async_in change");
    end else begin
        $display("Test passed: sync_out is 0 after async_in change");
    end
    $finish;
    

    
end
    
endmodule

tb_two_ff.vcd
$date
	Mon Aug 03 18:33:23 2026
$end
$version
	Icarus Verilog
$end
$timescale
	1s
$end
$scope module tb_two_ff $end
$var wire 1 ! sync_out $end
$var reg 1 " async_in $end
$var reg 1 # clk $end
$var reg 1 $ rst_n $end
$scope module uut $end
$var wire 1 " async_in $end
$var wire 1 # clk $end
$var wire 1 $ rst_n $end
$var wire 1 ! sync_out $end
$var reg 1 % ff1 $end
$var reg 1 & ff2 $end
$upscope $end
$upscope $end
$enddefinitions $end
$comment Show the parameter values. $end
$dumpall
$end
#0
$dumpvars
0&
0%
0$
0#
0"
0!
$end
#5
1#
#10
0#
#15
1#
#20
1$
0#
#25
1#
#30
1"
0#
#35
1%
1#
#40
0#
#45
1!
1&
1#
#50
0"
0#
#55
0%
1#
#60
0#
#65
0!
0&
1#
#70
0#
#71
1"
#74
0"
