programmable_counter.vhd
library ieee;
use ieee.std_logic_1164.all;
use ieee.numeric_std.all;

entity programmable_counter is
    generic (
        N : integer := 8  -- Width of the counter
    );
    port (
        clk     : in  std_logic;          -- Clock input
        rst_n   : in  std_logic;          -- Asynchronous reset input
        enable  : in  std_logic;          -- Enable input
        load    : in  std_logic;          -- Load input
        load_value : in  std_logic_vector(N-1 downto 0); -- Value to load into the counter
        limit_value : in  std_logic_vector(N-1 downto 0); -- Limit value for the counter
        count   : out std_logic_vector(N-1 downto 0);  -- Counter output
        limit_pulse : out std_logic          -- Limit pulse output
    );
end entity programmable_counter;

architecture rtl of programmable_counter is
    signal counter_reg : std_logic_vector(N-1 downto 0) := (others => '0');
    signal limit_reached : std_logic := '0';
    begin
        count <= counter_reg;
        limit_pulse <= limit_reached;
        process(clk, rst_n)
        begin
            if rst_n = '0' then
                counter_reg <= (others => '0');
                limit_reached <= '0';
            elsif rising_edge(clk) then 
                limit_reached <= '0';

                if load = '1' then
                    counter_reg <= load_value;

                elsif enable ='1' then
                    if (counter_reg = limit_value) then
                        counter_reg <= (others => '0');
                        limit_reached <='1';
                    else
                        counter_reg <= std_logic_vector(unsigned (counter_reg)+1);
                        limit_reached <= '0';

    end if;
    end if;
    end if;
    end process;
end architecture rtl;

tb_counter.sv
module tb_counter;

    parameter int unsigned WIDTH = 8;

    logic                 clk;
    logic                 rst_n;
    logic                 enable;
    logic                 load;
    logic [WIDTH-1:0]     load_value;
    logic [WIDTH-1:0]     limit_value;
    logic [WIDTH-1:0]     count;
    logic                 limit_pulse;

    integer error_count;

    programmable_counter #(.WIDTH(WIDTH)) dut (
        .clk(clk),
        .rst_n(rst_n),
        .enable(enable),
        .load(load),
        .load_value(load_value),
        .limit_value(limit_value),
        .count(count),
        .limit_pulse(limit_pulse)
    );

    task check_outputs;
    input [WIDTH-1:0] expected_count;
    input expected_limit_pulse;
    begin
        if(count !== expected_count) begin
            $display("Error: Expected count = %0d, but got %0d", expected_count, count);
            error_count++;
        end

        if(limit_pulse !== expected_limit_pulse) begin
            $display("Error: Expected limit_pulse = %0b, but got %0b", expected_limit_pulse, limit_pulse);
            error_count++;
        end
    end
    endtask

    initial begin
        // clock generation
        clk = 0;
        forever #5 clk = ~clk; // 10 time units clock period
    end

    initial begin
        $dumpfile("tb_counter.vcd");
        $dumpvars(0, tb_counter);

        error_count = 0;
        rst_n = 0;
        enable = 0;
        load = 0;
        load_value = 8'd2;
        limit_value = 8'd4;

        #1;
        check_outputs(0, 0);

        @(negedge clk);
        rst_n = 1;

        load = 1;
        @(posedge clk);
        @(negedge clk);
        check_outputs(2, 0);

        load = 0;
        enable = 1;

        @(posedge clk);
        @(negedge clk);
        check_outputs(3, 0);

        @(posedge clk);
        @(negedge clk);
        check_outputs(4, 0);

        @(posedge clk);
        @(negedge clk);
        check_outputs(0, 1);

        @(posedge clk);
        @(negedge clk);
        check_outputs(1, 0);

        enable = 0;

        @(posedge clk);
        @(negedge clk);
        check_outputs(1, 0);

        load = 1;
        load_value = 8'd3;
        enable = 1;

        @(posedge clk);
        @(negedge clk);
        check_outputs(3, 0);

        load = 0;
        @(posedge clk);
        @(negedge clk);
        check_outputs(4, 0);

        if(error_count == 0) begin
            $display("All tests passed!");
        end else begin
            $display("Total errors: %0d", error_count);
        end
        $finish;

    end


endmodule

testbench.vcd
$date
	Sun Jul 19 18:09:30 2026
$end
$version
	Icarus Verilog
$end
$timescale
	1ps
$end
$scope module tb_counter $end
$var wire 1 ! limit_pulse $end
$var wire 8 " count [7:0] $end
$var parameter 32 # WIDTH $end
$var reg 1 $ clk $end
$var reg 1 % enable $end
$var reg 8 & limit_value [7:0] $end
$var reg 1 ' load $end
$var reg 8 ( load_value [7:0] $end
$var reg 1 ) rst_n $end
$var integer 32 * error_count [31:0] $end
$scope module uut $end
$var wire 1 $ clk $end
$var wire 1 % enable $end
$var wire 8 + limit_value [7:0] $end
$var wire 1 ' load $end
$var wire 8 , load_value [7:0] $end
$var wire 1 ) rst_n $end
$var parameter 32 - WIDTH $end
$var reg 8 . count [7:0] $end
$var reg 1 ! limit_pulse $end
$upscope $end
$scope task check_outputs $end
$var reg 8 / expected_count [7:0] $end
$var reg 1 0 expected_limit_pulse $end
$upscope $end
$upscope $end
$enddefinitions $end
$comment Show the parameter values. $end
$dumpall
b1000 -
b1000 #
$end
#0
$dumpvars
x0
bx /
b0 .
b10 ,
b100 +
b0 *
0)
b10 (
0'
b100 &
0%
0$
b0 "
0!
$end
#1000
00
b0 /
#5000
1$
#10000
1'
1)
0$
#15000
b10 "
b10 .
1$
#20000
1%
0'
b10 /
0$
#25000
b11 "
b11 .
1$
#30000
b11 /
0$
#35000
b100 "
b100 .
1$
#40000
b100 /
0$
#45000
1!
b0 "
b0 .
1$
#50000
10
b0 /
0$
#55000
b1 "
b1 .
0!
1$
#60000
0%
00
b1 /
0$
#65000
1$
#70000
1%
1'
b11 (
b11 ,
0$
#75000
b11 "
b11 .
1$
#80000
0'
b11 /
0$
#85000
b100 "
b100 .
1$
#90000
b100 /
0$
